mpl_sizes/__init__.py
mpl_sizes/format.py
mpl_sizes/paper_formats/__init__.py
mpl_sizes/paper_formats/iclr.py
mpl_sizes/paper_formats/icml.py
mpl_sizes/paper_formats/inf_thesis.py
mpl_sizes/paper_formats/neurips.py
mpl_sizes-0.0.1.dist-info/METADATA
mpl_sizes-0.0.1.dist-info/WHEEL
mpl_sizes-0.0.1.dist-info/top_level.txt
mpl_sizes-0.0.1.dist-info/RECORD
