Metadata-Version: 2.1
Name: mpl-sizes
Version: 0.0.1
Summary: Default figure sizes for matplotlib.
Home-page: https://github.com/BayesWatch/matplotlib_size_sheets
Author: Jack Turner
Author-email: jackwilliamturner@icloud.com
License: UNKNOWN
Project-URL: Bug Tracker, https://github.com/BayesWatch/matplotlib_size_sheets/issues
Platform: UNKNOWN
Classifier: Programming Language :: Python :: 3
Classifier: License :: OSI Approved :: GNU General Public License v3 (GPLv3)
Classifier: Operating System :: OS Independent
Requires-Python: >=3.8
